{
    "city": "广东省",
    "data": {
        "Remain_confirm": {
            "end_date": "2020-03-01",
            "start_date": "2020-02-20",
            "value": [
                656,
                620,
                587,
                555,
                526,
                498,
                472,
                434,
                409,
                386,
                363
            ]
        },
        "predict": {
            "end_date": "2020-03-01",
            "start_date": "2020-02-20",
            "interval_high": [
                1398,
                1404,
                1410,
                1416,
                1422,
                1428,
                1433,
                1433,
                1435,
                1437,
                1439
            ],
            "value": [
                1326,
                1332,
                1338,
                1343,
                1349,
                1355,
                1360,
                1360,
                1362,
                1364,
                1366
            ],
            "interval_low": [
                1256,
                1261,
                1267,
                1273,
                1278,
                1284,
                1289,
                1289,
                1291,
                1292,
                1294
            ]
        },
        "official_confirmed": {
            "end_date": "2020-02-27",
            "start_date": "2020-02-20",
            "value": [
                1333,
                1339,
                1342,
                1345,
                1347,
                1347,
                1347,
                1348
            ]
        },
        "inflection_left": -24,
        "remain_peak_left": -16
    },
    "province": "广东省"
}